libido.py
libido-0.0.9.dist-info/METADATA
libido-0.0.9.dist-info/WHEEL
libido-0.0.9.dist-info/entry_points.txt
libido-0.0.9.dist-info/top_level.txt
libido-0.0.9.dist-info/RECORD
