Metadata-Version: 2.1
Name: libido
Version: 0.0.9
Summary: Discover which libs are imported by a set of python files
Home-page: https://github.com/aluriak/libido
Author: Lucas Bourneuf
Author-email: lucas@bourneuf.net
License: GPLv3
Keywords: stdlib,static analysis
Platform: UNKNOWN
Classifier: License :: OSI Approved :: GNU General Public License v3 (GPLv3)
Classifier: Development Status :: 4 - Beta
Classifier: Programming Language :: Python :: 3
Classifier: Programming Language :: Python :: 3.5
Classifier: Programming Language :: Python :: 3.6
Classifier: Programming Language :: Python :: 3.7
Classifier: Programming Language :: Python :: 3.8
Classifier: Programming Language :: Python :: 3.9
Classifier: Programming Language :: Python :: 3.10
Requires-Dist: redbaron (==0.9.2)
Requires-Dist: stdlibs (==2022.3.16)
